{
  "$schema": "../gen/schemas/desktop-schema.json",
  "identifier": "default",
  "description": "Capability for the main window",
  "windows": ["main", "note"],
  "permissions": [
    "core:default",
    "opener:default",
    "core:window:default",
    "core:window:allow-start-dragging",
    "core:window:allow-set-always-on-top",
    "core:window:allow-close",
    "core:webview:allow-create-webview-window",
    "core:webview:allow-create-webview",
    "core:window:allow-minimize",
    "core:window:allow-toggle-maximize",
    "fs:default",
    "fs:allow-read-text-file",
    "fs:allow-write-text-file",
    "fs:allow-create",
    "fs:allow-remove",
    "fs:allow-rename",
    "fs:allow-resource-read-recursive",
    "fs:allow-resource-write-recursive",
    {
      "identifier": "fs:allow-exists",
      "allow": [
        {
          "path": "$AppData/*"
        }
      ]
    }
  ]
}
